{
  "hash": "6f8e51ae",
  "configHash": "9a34307c",
  "lockfileHash": "b1c1dd64",
  "browserHash": "df16249d",
  "optimized": {
    "vue": {
      "src": "../../../../node_modules/.pnpm/vue@3.4.35_typescript@5.5.4/node_modules/vue/dist/vue.runtime.esm-bundler.js",
      "file": "vue.js",
      "fileHash": "4750d33a",
      "needsInterop": false
    },
    "vitepress > @vue/devtools-api": {
      "src": "../../../../node_modules/.pnpm/@vue+devtools-api@7.3.7/node_modules/@vue/devtools-api/dist/index.js",
      "file": "vitepress___@vue_devtools-api.js",
      "fileHash": "56faca21",
      "needsInterop": false
    },
    "vitepress > @vueuse/core": {
      "src": "../../../../node_modules/.pnpm/@vueuse+core@10.11.0_vue@3.4.35_typescript@5.5.4_/node_modules/@vueuse/core/index.mjs",
      "file": "vitepress___@vueuse_core.js",
      "fileHash": "1f1bd838",
      "needsInterop": false
    },
    "@vicons/ionicons5": {
      "src": "../../../../node_modules/.pnpm/@vicons+ionicons5@0.12.0/node_modules/@vicons/ionicons5/es/index.js",
      "file": "@vicons_ionicons5.js",
      "fileHash": "301dd910",
      "needsInterop": false
    }
  },
  "chunks": {
    "chunk-ARQM6S7H": {
      "file": "chunk-ARQM6S7H.js"
    }
  }
}